[{"s": "sfera-kurer-kak-otpravit-dokument-na-ozon", "t": "Как отправить документ на Озон через курьера: пошаговая инструкция 2026", "i": "🚚", "c": "dostavka-i-pvz"}, {"s": "sfera-deyatelnosti-na-ozon-chto-pisat-v-grafe", "t": "Сфера деятельности на Ozon: что писать в графе для селлера", "i": "📁", "c": null}, {"s": "sfera-deyatelnosti-na-ozon-chto-vybrat", "t": "Сфера деятельности на Ozon: что выбрать для старта в 2026", "i": "📁", "c": null}, {"s": "sfera-kurer-ili-kontur-diadok-dlya-ozon-chto-luchshe", "t": "Сфера или Диадок для Ozon: сравнение ЭДО", "i": "🚀", "c": "start-dlya-sellera"}]